README.md
setup.py
google_sheets_db/__init__.py
google_sheets_db/base_sheet.py
google_sheets_db/database.py
google_sheets_db/field.py
google_sheets_db.egg-info/PKG-INFO
google_sheets_db.egg-info/SOURCES.txt
google_sheets_db.egg-info/dependency_links.txt
google_sheets_db.egg-info/requires.txt
google_sheets_db.egg-info/top_level.txt