Metadata-Version: 2.1
Name: google-sheets-db
Version: 1.0.8
Summary: Google Sheets as a database ORM
Home-page: https://github.com/egorgvo/google-sheets-db
Author: Egor Gvo
Author-email: work.egvo@ya.ru
License: MIT
Platform: UNKNOWN
Classifier: License :: OSI Approved :: MIT License
Classifier: Programming Language :: Python :: 3
